{"stats":{"minecraft:picked_up":{"minecraft:stone":287,"minecraft:golden_carrot":24,"minecraft:tripwire_hook":4989,"minecraft:quartz":64,"minecraft:gravel":1,"minecraft:flint":4,"minecraft:diorite":49,"minecraft:trident":2,"minecraft:arrow":8,"minecraft:deepslate":25,"minecraft:wheat_seeds":14,"minecraft:emerald":830,"minecraft:poppy":2,"minecraft:cobblestone":4,"minecraft:diamond_pickaxe":1},"minecraft:custom":{"minecraft:time_since_rest":2332,"minecraft:sprint_one_cm":31934,"minecraft:damage_taken":681,"minecraft:walk_one_cm":31198,"minecraft:drop":120,"minecraft:damage_dealt":275,"minecraft:traded_with_villager":4,"minecraft:talked_to_villager":1,"minecraft:swim_one_cm":3052,"minecraft:interact_with_crafting_table":1,"minecraft:fly_one_cm":61326,"minecraft:open_chest":21,"minecraft:crouch_one_cm":825,"minecraft:play_time":26907,"minecraft:open_shulker_box":3,"minecraft:deaths":2,"minecraft:sneak_time":610,"minecraft:walk_under_water_one_cm":410,"minecraft:jump":286,"minecraft:leave_game":1,"minecraft:time_since_death":1705,"minecraft:walk_on_water_one_cm":3141,"minecraft:total_world_time":26907,"minecraft:fall_one_cm":6201},"minecraft:killed_by":{"minecraft:zombie":2},"minecraft:mined":{"minecraft:shulker_box":1,"minecraft:short_grass":2,"minecraft:coal_ore":10,"minecraft:copper_ore":5,"minecraft:cobblestone":3,"minecraft:stone":404,"minecraft:diorite":130,"minecraft:deepslate":25},"minecraft:crafted":{"minecraft:diamond_helmet":1,"minecraft:diamond_leggings":1,"minecraft:diamond_boots":1,"minecraft:diamond_chestplate":1},"minecraft:used":{"minecraft:trident":8,"minecraft:diamond_pickaxe":578,"minecraft:stone":103,"minecraft:deepslate":17,"minecraft:gravel":1,"minecraft:cobblestone":4,"minecraft:golden_carrot":2},"minecraft:dropped":{"minecraft:poppy":2,"minecraft:wheat_seeds":1,"minecraft:trident":4,"minecraft:diorite":6,"minecraft:arrow":6,"minecraft:tripwire_hook":6731,"minecraft:emerald":87,"minecraft:flint":4}},"DataVersion":4189}